nostr/__init__.py
nostr/_version.py
nostr/bech32.py
nostr/cli.py
nostr/delegation.py
nostr/event.py
nostr/filter.py
nostr/key.py
nostr/message_pool.py
nostr/message_type.py
nostr/pow.py
nostr/relay.py
nostr/relay_manager.py
nostr/request.py
nostr/subscription.py
nostr/utils.py
nostr/commands/README.md
nostr/commands/config.py
nostr/commands/key.py
nostr/commands/message.py
nostr/sample/config.hcl
nostrpy-0.6.0.dist-info/LICENSE
nostrpy-0.6.0.dist-info/METADATA
nostrpy-0.6.0.dist-info/WHEEL
nostrpy-0.6.0.dist-info/entry_points.txt
nostrpy-0.6.0.dist-info/top_level.txt
nostrpy-0.6.0.dist-info/RECORD
