Metadata-Version: 2.1
Name: nostrpy
Version: 0.6.0
Summary: Python CLI for Nostr
Author-email: Richard Li <lifuzu+github@gmail.com>
License: MIT License
Project-URL: Homepage, https://github.com/nostrpy/nostrcli
Classifier: Operating System :: POSIX :: Linux
Classifier: Operating System :: Microsoft :: Windows
Classifier: Operating System :: MacOS :: MacOS X
Requires-Python: >=3.7.0
License-File: LICENSE
Requires-Dist: coincurve (>=18.0.0)
Requires-Dist: cryptography (>=38.0.4)
Requires-Dist: websocket-client (>=1.4.2)
Requires-Dist: click (>=8.1.3)
Requires-Dist: click-aliases (>=1.0.1)
Requires-Dist: python-hcl2 (>=4.3.0)
Provides-Extra: test
Requires-Dist: pytest (>=7.2.0) ; extra == 'test'
Requires-Dist: pytest-cov[all] ; extra == 'test'
Requires-Dist: pre-commit (>=3.1.0) ; extra == 'test'
